MANIFEST.in
setup.cfg
setup.py
./setup.py
./build/lib/src/__init__.py
./build/lib/src/adminapp.py
./build/lib/src/server.py
./src/__init__.py
./src/adminapp.py
./src/server.py
./src/log/server_log_config.py
gb_cat4er_chat_server.egg-info/PKG-INFO
gb_cat4er_chat_server.egg-info/SOURCES.txt
gb_cat4er_chat_server.egg-info/dependency_links.txt
gb_cat4er_chat_server.egg-info/top_level.txt
src/__init__.py
src/adminapp.py
src/server.py